ngpt/__init__.py
ngpt/__main__.py
ngpt/version.py
ngpt/api/__init__.py
ngpt/api/client.py
ngpt/cli/__init__.py
ngpt/cli/args.py
ngpt/cli/main.py
ngpt/cli/handlers/__init__.py
ngpt/cli/handlers/api_config_handler.py
ngpt/cli/handlers/cli_config_handler.py
ngpt/cli/handlers/client_handler.py
ngpt/cli/handlers/error_handler.py
ngpt/cli/handlers/log_handler.py
ngpt/cli/handlers/models.py
ngpt/cli/handlers/modes_handler.py
ngpt/cli/handlers/role.py
ngpt/cli/handlers/session_handler.py
ngpt/cli/modes/__init__.py
ngpt/cli/modes/chat.py
ngpt/cli/modes/code.py
ngpt/cli/modes/gitcommsg.py
ngpt/cli/modes/interactive.py
ngpt/cli/modes/rewrite.py
ngpt/cli/modes/shell.py
ngpt/cli/modes/text.py
ngpt/core/__init__.py
ngpt/core/cli_config.py
ngpt/core/config.py
ngpt/core/log.py
ngpt/ui/__init__.py
ngpt/ui/colors.py
ngpt/ui/formatters.py
ngpt/ui/interactive_ui.py
ngpt/ui/pipe.py
ngpt/ui/renderers.py
ngpt/ui/session_ui.py
ngpt/ui/tables.py
ngpt/ui/tui.py
ngpt/utils/__init__.py
ngpt/utils/web_search.py
ngpt-6.7.4.dist-info/METADATA
ngpt-6.7.4.dist-info/WHEEL
ngpt-6.7.4.dist-info/entry_points.txt
ngpt-6.7.4.dist-info/licenses/LICENSE
ngpt-6.7.4.dist-info/RECORD
