Metadata-Version: 2.4
Name: ngpt
Version: 6.7.4
Summary: A lightning-fast AI-powered CLI toolkit for terminal productivity. Generate code, craft git commits, execute shell commands, and chat with any OpenAI-compatible LLM (OpenAI, Ollama, Groq, Claude, Gemini) directly from your terminal.
Project-URL: Homepage, https://github.com/nazdridoy/ngpt
Project-URL: Repository, https://github.com/nazdridoy/ngpt
Project-URL: Bug Tracker, https://github.com/nazdridoy/ngpt/issues
Author-email: nazDridoy <nazdridoy399@gmail.com>
License: MIT
License-File: LICENSE
Keywords: ai,api-client,chatbot,chatgpt,claude,cli,cli-tool,code-generation,git-commit,gpt,groq,llm,markdown-rendering,ollama,openai,shell-commands,text-rewriting
Classifier: Environment :: Console
Classifier: Intended Audience :: Developers
Classifier: Intended Audience :: End Users/Desktop
Classifier: Intended Audience :: System Administrators
Classifier: License :: OSI Approved :: MIT License
Classifier: Operating System :: OS Independent
Classifier: Programming Language :: Python :: 3
Classifier: Programming Language :: Python :: 3.8
Classifier: Programming Language :: Python :: 3.9
Classifier: Programming Language :: Python :: 3.10
Classifier: Programming Language :: Python :: 3.11
Classifier: Programming Language :: Python :: 3.12
Classifier: Programming Language :: Python :: 3.13
Classifier: Topic :: Communications :: Chat
Classifier: Topic :: Internet :: WWW/HTTP
Classifier: Topic :: Scientific/Engineering :: Artificial Intelligence
Classifier: Topic :: Software Development :: Libraries :: Python Modules
Classifier: Topic :: Utilities
Requires-Python: >=3.8
Requires-Dist: beautifulsoup4>=4.12.0
Requires-Dist: prompt-toolkit>=3.0.0
Requires-Dist: pyperclip>=1.8.0
Requires-Dist: requests>=2.31.0
Requires-Dist: rich>=10.0.0
